Metadata-Version: 2.1
Name: odoo12-addon-webservice
Version: 12.0.1.0.0.99.dev5
Summary: Defines webservice abstract definition to be used generally
Home-page: https://github.com/OCA/web-api
Author: Creu Blanca, Camptocamp, Odoo Community Association (OCA)
Author-email: support@odoo-community.org
License: AGPL-3
Classifier: Programming Language :: Python
Classifier: Framework :: Odoo
Classifier: Framework :: Odoo :: 12.0
Classifier: License :: OSI Approved :: GNU Affero General Public License v3
Classifier: Development Status :: 5 - Production/Stable
Requires-Python: >=3.5
Requires-Dist: odoo12-addon-component
Requires-Dist: odoo12-addon-server-environment
Requires-Dist: odoo<12.1dev,>=12.0a
